smore/__init__.py
smore/exceptions.py
smore/apispec/__init__.py
smore/apispec/core.py
smore/apispec/exceptions.py
smore/apispec/utils.py
smore/ext/__init__.py
smore/ext/flask.py
smore/ext/marshmallow.py
smore/swagger/__init__.py
smore-0.2.0.dist-info/DESCRIPTION.rst
smore-0.2.0.dist-info/METADATA
smore-0.2.0.dist-info/metadata.json
smore-0.2.0.dist-info/RECORD
smore-0.2.0.dist-info/top_level.txt
smore-0.2.0.dist-info/WHEEL
