Metadata-Version: 2.0
Name: smore
Version: 0.2.0
Summary: A collection of utilities for designing and documenting RESTful APIs. Currently experimental.
Home-page: https://github.com/marshmallow-code/smore
Author: Steven Loria, Josh Carp
Author-email: sloria1@gmail.com
License: Copyright 2015 Steven Loria, Josh Carp, and contributors
Requires-Dist: marshmallow (>=1.2.0)
Requires-Dist: PyYAML (>=3.10)
